notas_unip/__init__.py
notas_unip/md.py
notas_unip/mf.py
notas_unip/rounding.py
notas_unip-0.1.0.dist-info/LICENSE
notas_unip-0.1.0.dist-info/METADATA
notas_unip-0.1.0.dist-info/WHEEL
notas_unip-0.1.0.dist-info/RECORD
